{
  "ok": true,
  "date": "2026-05-11",
  "data": {
    "last_updated": "2026-05-11T22:17:37.326320+09:00",
    "pipeline_status": "success",
    "ai_recommendation": {
      "sectors": [
        "반도체",
        "바이오/헬스케어",
        "소비재"
      ],
      "reason": "반도체는 미국 시장의 강력한 긍정적 뉴스 점수와 한국 시장 내 압도적인 거래대금을 바탕으로 내일도 시장의 주요 관심 섹터가 될 것으로 예상됩니다. 바이오/헬스케어는 한국 시장에서 매우 높은 긍정 뉴스 점수를 기록하여 긍정적인 모멘텀이 형성될 가능성이 높습니다. 소비재는 한국과 미국 양쪽에서 꾸준히 긍정적인 뉴스 흐름을 보여 안정적인 관심이 지속될 것으로 판단됩니다.",
      "confidence": 0.85,
      "generated_at": "2026-05-11T22:17:37.326320+09:00"
    },
    "korea_sector_ranking": [
      {
        "sector": "바이오/헬스케어",
        "score": 7.83,
        "sentiment": "positive"
      },
      {
        "sector": "소비재",
        "score": 7.21,
        "sentiment": "positive"
      },
      {
        "sector": "기타",
        "score": 0.0,
        "sentiment": "negative"
      }
    ],
    "us_sector_ranking": [
      {
        "sector": "철강/소재",
        "score": 9.0,
        "sentiment": "positive"
      },
      {
        "sector": "반도체",
        "score": 8.88,
        "sentiment": "positive"
      },
      {
        "sector": "IT/소프트웨어",
        "score": 8.0,
        "sentiment": "positive"
      },
      {
        "sector": "소비재",
        "score": 6.5,
        "sentiment": "positive"
      },
      {
        "sector": "금융",
        "score": 5.6,
        "sentiment": "neutral"
      },
      {
        "sector": "기타",
        "score": 0.0,
        "sentiment": "negative"
      }
    ],
    "korea_sector_volume_distribution": [
      {
        "sector": "반도체",
        "volume_amount": 25128776148871,
        "ratio": 0.4565
      },
      {
        "sector": "기타",
        "volume_amount": 20096342355536,
        "ratio": 0.365
      },
      {
        "sector": "자동차",
        "volume_amount": 3602921677135,
        "ratio": 0.0654
      },
      {
        "sector": "조선/방산",
        "volume_amount": 1997927171175,
        "ratio": 0.0363
      },
      {
        "sector": "2차전지",
        "volume_amount": 1356233643050,
        "ratio": 0.0246
      },
      {
        "sector": "부동산/건설",
        "volume_amount": 1026433644575,
        "ratio": 0.0186
      },
      {
        "sector": "금융",
        "volume_amount": 815989551850,
        "ratio": 0.0148
      },
      {
        "sector": "통신/미디어",
        "volume_amount": 386015543045,
        "ratio": 0.007
      },
      {
        "sector": "철강/소재",
        "volume_amount": 257435288500,
        "ratio": 0.0047
      },
      {
        "sector": "바이오/헬스케어",
        "volume_amount": 166759709650,
        "ratio": 0.003
      },
      {
        "sector": "에너지",
        "volume_amount": 116981710300,
        "ratio": 0.0021
      },
      {
        "sector": "소비재",
        "volume_amount": 100578766500,
        "ratio": 0.0018
      }
    ],
    "us_sector_volume_distribution": []
  }
}